infinity/__init__.py
infinity/utils.py
infinity/login/__init__.py
infinity/login/client_exceptions.py
infinity/login/constants.py
infinity/login/infinity_login.py
infinity/rest_client/__init__.py
infinity/rest_client/client_exceptions.py
infinity/rest_client/constants.py
infinity/rest_client/rest_client.py
infinity/websocket_client/__init__.py
infinity/websocket_client/constants.py
infinity/websocket_client/websocket_client.py
infinity/websocket_client/websocket_handler.py
python_infinity-0.0.7.dist-info/LICENSE
python_infinity-0.0.7.dist-info/METADATA
python_infinity-0.0.7.dist-info/WHEEL
python_infinity-0.0.7.dist-info/top_level.txt
python_infinity-0.0.7.dist-info/RECORD
