Metadata-Version: 2.1
Name: python-infinity
Version: 0.0.7
Summary: Unofficial Infinity client packages
Author-email: pydevbuzz <pydevbuzz@gmail.com>
Project-URL: Homepage, https://github.com/pydevbuzz/python-infinity
Project-URL: Bug Tracker, https://github.com/pydevbuzz/python-infinity/issues
Classifier: Programming Language :: Python :: 3
Classifier: License :: OSI Approved :: MIT License
Classifier: Operating System :: OS Independent
Requires-Python: <3.11.6,>=3.11.0
License-File: LICENSE
Requires-Dist: requests >=2.31.0
Requires-Dist: web3 ~=6.11.2
Requires-Dist: websocket-client ~=1.6.2
